KUKA/KUKA.py
KUKA/SSH.py
KUKA/__init__.py
KUKA/service.py
KUKA_youbot-0.1.2.dist-info/LICENSE
KUKA_youbot-0.1.2.dist-info/METADATA
KUKA_youbot-0.1.2.dist-info/WHEEL
KUKA_youbot-0.1.2.dist-info/top_level.txt
KUKA_youbot-0.1.2.dist-info/RECORD
