Metadata-Version: 2.1
Name: KUKA-youbot
Version: 0.1.2
Summary: package for easy KUKA-youbot control
Author-email: ZaSKaR <mark.turkov@mail.ru>
Project-URL: Homepage, https://github.com/MarkT5/YouBotKUKA
Project-URL: Bug Tracker, https://github.com/MarkT5/YouBotKUKA/issues
Project-URL: repository, https://github.com/MarkT5/YouBotKUKA
Requires-Python: >=3.8
License-File: LICENSE
Requires-Dist: setuptools (>=40.9.0)
Requires-Dist: numpy (>=1.23.0)
Requires-Dist: opencv-python (>=4.7.0.72)
Requires-Dist: py-mjpeg (>=1.0.1)
Requires-Dist: paramiko (>=3.1.0)
Requires-Dist: Pillow (>=9.4.0)
